litepolis_ui_example/__init__.py
litepolis_ui_example/core.py
litepolis_ui_example-0.0.1.dist-info/licenses/LICENSE
litepolis_ui_example-0.0.1.dist-info/METADATA
litepolis_ui_example-0.0.1.dist-info/WHEEL
litepolis_ui_example-0.0.1.dist-info/top_level.txt
litepolis_ui_example-0.0.1.dist-info/RECORD
