Metadata-Version: 2.4
Name: litepolis-ui-example
Version: 0.0.1
Summary: The user interface template module for LitePolis
Home-page: https://github.com/NewJerseyStyle/LitePolis-ui-example
Author: NewJerseyStyle
License: MIT License
License-File: LICENSE
Requires-Dist: fastapi
Requires-Dist: litepolis
Dynamic: author
Dynamic: description
Dynamic: description-content-type
Dynamic: home-page
Dynamic: license
Dynamic: license-file
Dynamic: requires-dist
Dynamic: summary
